serialization/__init__.py
serialization/serialize.py
xrdpattern/__init__.py
xrdpattern/xrd_file_io/__init__.py
xrdpattern/xrd_file_io/formats.py
xrdpattern/xrd_file_io/read_write.py
xrdpattern/xrd_file_io/xyconv.py
xrdpattern/xrd_logger/__init__.py
xrdpattern/xrd_logger/logger.py
xrdpattern/xrd_types/__init__.py
xrdpattern/xrd_types/metadata.py
xrdpattern/xrd_types/pattern.py
xrdpattern/xrd_types/pattern_db.py
xrdpattern/xrd_types/report.py
xrdpattern-0.7.4.dist-info/METADATA
xrdpattern-0.7.4.dist-info/WHEEL
xrdpattern-0.7.4.dist-info/top_level.txt
xrdpattern-0.7.4.dist-info/RECORD
