Metadata-Version: 2.1
Name: xrdpattern
Version: 0.7.4
Summary: Python library for XrdPatterns including file import, file export, plotting and postprocessing functionalities
Home-page: https://github.com/aimat-lab/xrdpattern
Author: Daniel Hollarek
Author-email: daniel.hollarek@googlemail.com
Requires-Python: >=3.8
Requires-Dist: numpy
Requires-Dist: scipy
Requires-Dist: matplotlib
Requires-Dist: xylib-py-fixed-RawV4
Requires-Dist: hollarek ==0.5.3
